attack_query_mcp/__init__.py
attack_query_mcp/resources.py
attack_query_mcp/server.py
attack_query_mcp/tools.py
attack_query_mcp-0.4.1.dist-info/METADATA
attack_query_mcp-0.4.1.dist-info/WHEEL
attack_query_mcp-0.4.1.dist-info/entry_points.txt
attack_query_mcp-0.4.1.dist-info/licenses/LICENSE
attack_query_mcp-0.4.1.dist-info/RECORD
