Metadata-Version: 2.4
Name: attack-query-mcp
Version: 0.4.1
Summary: MCP server for ATT&CK queries via AI assistants
Project-URL: Homepage, https://github.com/swoodeng/attack-query
Project-URL: Repository, https://github.com/swoodeng/attack-query
Project-URL: Documentation, https://github.com/swoodeng/attack-query#readme
Project-URL: Issues, https://github.com/swoodeng/attack-query/issues
Author: Stephen Wood
License: MIT
License-File: LICENSE
Keywords: ai,attack,claude,llm,mcp,mitre,threat-intelligence
Classifier: Development Status :: 3 - Alpha
Classifier: Intended Audience :: Developers
Classifier: License :: OSI Approved :: MIT License
Classifier: Operating System :: OS Independent
Classifier: Programming Language :: Python :: 3
Classifier: Programming Language :: Python :: 3.10
Classifier: Programming Language :: Python :: 3.11
Classifier: Programming Language :: Python :: 3.12
Classifier: Programming Language :: Python :: 3.13
Classifier: Topic :: Security
Requires-Python: >=3.10
Requires-Dist: attack-query>=0.6.0
Requires-Dist: mcp<2,>=1.2.5
Provides-Extra: dev
Requires-Dist: pytest-asyncio>=0.23.0; extra == 'dev'
Requires-Dist: pytest>=8.0.0; extra == 'dev'
Requires-Dist: ruff>=0.4.0; extra == 'dev'
